monotonic_alignment_search/__init__.py
monotonic_alignment_search/core.c
monotonic_alignment_search/core.cpython-311-x86_64-linux-musl.so
monotonic_alignment_search/core.pyi
monotonic_alignment_search/core.pyx
monotonic_alignment_search/path.py
monotonic_alignment_search/py.typed
monotonic_alignment_search-0.2.1.dist-info/METADATA
monotonic_alignment_search-0.2.1.dist-info/WHEEL
monotonic_alignment_search-0.2.1.dist-info/top_level.txt
monotonic_alignment_search-0.2.1.dist-info/RECORD
monotonic_alignment_search-0.2.1.dist-info/licenses/LICENSE
